grblcom/__init__.py
grblcom/__main__.py
grblcom/commands.py
grblcom/grbl.py
grblcom/repl.py
grblcom/utils.py
grblcom-0.0.0.dist-info/DESCRIPTION.rst
grblcom-0.0.0.dist-info/METADATA
grblcom-0.0.0.dist-info/RECORD
grblcom-0.0.0.dist-info/WHEEL
grblcom-0.0.0.dist-info/metadata.json
grblcom-0.0.0.dist-info/top_level.txt
grblcom-0.0.0.dist-info/zip-safe
