Metadata-Version: 2.0
Name: grblcom
Version: 0.0.0
Summary: Rich serial-console client for GRBL
Home-page: https://github.com/gvalkov/grblcom
Author: Georgi Valkov
Author-email: georgi.t.valkov@gmail.com
License: Revised BSD License
Keywords: grbl
Platform: UNKNOWN
Classifier: Development Status :: 4 - Beta
Classifier: Programming Language :: Python :: 3
Classifier: Programming Language :: Python :: 3.3
Classifier: Programming Language :: Python :: 3.4
Classifier: Programming Language :: Python :: 3.5
Classifier: Programming Language :: Python :: 3.6
Classifier: License :: OSI Approved :: BSD License
Requires-Dist: prompt-toolkit (>=0.60)
Requires-Dist: pyserial (>=3.0)
Provides-Extra: devel
Requires-Dist: bumpversion (>=0.5.2); extra == 'devel'
Requires-Dist: check-manifest (>=0.35); extra == 'devel'
Requires-Dist: flake8; extra == 'devel'
Requires-Dist: pep8-naming; extra == 'devel'
Requires-Dist: readme-renderer (>=16.0); extra == 'devel'
Provides-Extra: tests
Requires-Dist: pytest (>=3.0.3); extra == 'tests'
Requires-Dist: pytest-cov (>=2.3.1); extra == 'tests'
Requires-Dist: tox (>=2.6.0); extra == 'tests'
